XDoToolWrapper/__init__.py
XDoToolWrapper-0.0.4.dist-info/METADATA
XDoToolWrapper-0.0.4.dist-info/WHEEL
XDoToolWrapper-0.0.4.dist-info/top_level.txt
XDoToolWrapper-0.0.4.dist-info/RECORD
